djfiler/__init__.py
djfiler/djfiler.py
djfiler/core/__init__.py
djfiler/core/file_upload.py
djfiler/core/founder.py
djfiler/core/logger.py
djfiler/core/namegen.py
djfiler-0.1.dist-info/LICENSE.txt
djfiler-0.1.dist-info/METADATA
djfiler-0.1.dist-info/WHEEL
djfiler-0.1.dist-info/top_level.txt
djfiler-0.1.dist-info/RECORD
