Metadata-Version: 2.1
Name: djfiler
Version: 0.1
Summary: This Module Upload and Host Any File Easy On Django
Home-page: https://github.com/E-RROR/django-filer
Author: Sina Farhadi
Author-email: sina.farhadi.cyber@gmail.com
License: UNKNOWN
Platform: UNKNOWN
Classifier: Programming Language :: Python :: 3
Classifier: License :: OSI Approved :: MIT License
Classifier: Operating System :: OS Independent
